odoo/addons/__init__.py
odoo/addons/crm/README.md
odoo/addons/crm/__init__.py
odoo/addons/crm/__manifest__.py
odoo/addons/crm/controllers/__init__.py
odoo/addons/crm/controllers/main.py
odoo/addons/crm/data/crm_data.xml
odoo/addons/crm/data/crm_demo.xml
odoo/addons/crm/data/crm_lead_data.xml
odoo/addons/crm/data/crm_lead_demo.xml
odoo/addons/crm/data/crm_stage_data.xml
odoo/addons/crm/data/mail_activity_demo.xml
odoo/addons/crm/data/mail_template_data.xml
odoo/addons/crm/data/web_planner_data.xml
odoo/addons/crm/doc/changelog.rst
odoo/addons/crm/doc/index.rst
odoo/addons/crm/doc/stage_status.rst
odoo/addons/crm/i18n/af.po
odoo/addons/crm/i18n/am.po
odoo/addons/crm/i18n/ar.po
odoo/addons/crm/i18n/bg.po
odoo/addons/crm/i18n/bs.po
odoo/addons/crm/i18n/ca.po
odoo/addons/crm/i18n/cs.po
odoo/addons/crm/i18n/da.po
odoo/addons/crm/i18n/de.po
odoo/addons/crm/i18n/el.po
odoo/addons/crm/i18n/en_GB.po
odoo/addons/crm/i18n/es.po
odoo/addons/crm/i18n/es_BO.po
odoo/addons/crm/i18n/es_CL.po
odoo/addons/crm/i18n/es_CO.po
odoo/addons/crm/i18n/es_CR.po
odoo/addons/crm/i18n/es_DO.po
odoo/addons/crm/i18n/es_EC.po
odoo/addons/crm/i18n/es_MX.po
odoo/addons/crm/i18n/es_PE.po
odoo/addons/crm/i18n/es_PY.po
odoo/addons/crm/i18n/es_VE.po
odoo/addons/crm/i18n/et.po
odoo/addons/crm/i18n/eu.po
odoo/addons/crm/i18n/fa.po
odoo/addons/crm/i18n/fi.po
odoo/addons/crm/i18n/fo.po
odoo/addons/crm/i18n/fr.po
odoo/addons/crm/i18n/fr_CA.po
odoo/addons/crm/i18n/gl.po
odoo/addons/crm/i18n/gu.po
odoo/addons/crm/i18n/he.po
odoo/addons/crm/i18n/hr.po
odoo/addons/crm/i18n/hu.po
odoo/addons/crm/i18n/id.po
odoo/addons/crm/i18n/is.po
odoo/addons/crm/i18n/it.po
odoo/addons/crm/i18n/ja.po
odoo/addons/crm/i18n/ka.po
odoo/addons/crm/i18n/kab.po
odoo/addons/crm/i18n/ko.po
odoo/addons/crm/i18n/lo.po
odoo/addons/crm/i18n/lt.po
odoo/addons/crm/i18n/lv.po
odoo/addons/crm/i18n/mk.po
odoo/addons/crm/i18n/mn.po
odoo/addons/crm/i18n/nb.po
odoo/addons/crm/i18n/ne.po
odoo/addons/crm/i18n/nl.po
odoo/addons/crm/i18n/nl_BE.po
odooku_odoo_crm-11.0.7.dist-info/LICENSE
odooku_odoo_crm-11.0.7.dist-info/METADATA
odooku_odoo_crm-11.0.7.dist-info/WHEEL
odooku_odoo_crm-11.0.7.dist-info/top_level.txt
odooku_odoo_crm-11.0.7.dist-info/RECORD
